Workbook
Name ExternalData_1: SummaryKPIs!$A$1:$K$3
Name Slicer_category_type2: #N/A
Name Slicer_KPIs: #N/A
Name Slicer_KPIs1: #N/A
Name Slicer_Parameter: #N/A

Sheet MainTable
A1: price_per_unit | B1: quality_score | C1: delivery_time_days | D1: on_time_delivery_rate | E1: defect_rate | F1: return_rate | G1: delivery_mode | H1: lead_time_variance | I1: forecast_accuracy | J1: seasonality_index | K1: demand_volatility_index | L1: order_frequency_monthly | M1: avg_order_volume | N1: payment_term_days | O1: offer_validity_days | P1: procurement_action_code | Q1: delivery_term_code | R1: items_requested | S1: items_offered | T1: temporal_month | U1: supplier_reliability_score | V1: selected_supplier_flag | W1: selection_status | X1: delivery_term | Y1: procurement_action | Z1: month_name | AA1: delivery_performance_score | AB1: order_accuracy | AC1: on_time_in_full | AD1: risk_score | AE1: risk_category | AF1: value_score | AG1: value_category | AH1: price_category | AI1: lead_time_category | AJ1: fulfillment_ratio percentage | AK1: fulfillment_category | AL1: shipping_cost_estimate | AM1: total_cost_impact | AN1: customer_satisfaction_estimate
A2: 218.54 | B2: 3.28 | C2: 13 | D2: 0.82 | E2: 0.01 | F2: 0.04 | G2: Sea | H2: 2.67 | I2: 0.64 | J2: 1.03 | K2: 0.03 | L2: 15 | M2: 3677.39 | N2: 30 | O2: 46 | P2: 3 | Q2: 0 | R2: 885 | S2: 423 | T2: 9 | U2: 0.6 | V2: 1 | W2: Selected | X2: EXW | Y2: Extension | Z2: September | AA2: 0.8118 | AB2: 0.9504 | AC2: 0.171072 | AD2: 0.08 | AE2: Low Risk | AF2: 0.015008694 | AG2: Poor | AH2: Medium | AI2: Inconsistent | AJ2: 47.79661 | AK2: Critical (<80%) | AL2: 36.7739 | AM2: 843888.1 | AN2: 72.23
A3: 477.82 | B3: 5.05 | C3: 2 | D3: 0.89 | E3: 0.06 | F3: 0.02 | G3: Road | H3: 1.68 | I3: 0.85 | J3: 0.84 | K3: 0.27 | L3: 44 | M3: 4533.31 | N3: 45 | O3: 19 | P3: 0 | Q3: 2 | R3: 941 | S3: 608 | T3: 11 | U3: 0.34 | V3: 0 | W3: Rejected | X3: CIF | Y3: New Procurement | Z3: November | AA3: 0.8366 | AB3: 0.9212 | AC3: 0.101332 | AD3: 0.35 | AE3: High Risk | AF3: 0.010568833 | AG3: Poor | AH3: High | AI3: Moderately Consistent | AJ3: 64.612115 | AK3: Critical (<80%) | AL3: 90.6662 | AM3: 2339501.4 | AN3: 84.12
A4: 379.4 | B4: 9.62 | C4: 2 | D4: 0.71 | E4: 0.07 | F4: 0.04 | G4: Sea | H4: 1.66 | I4: 0.7 | J4: 1.03 | K4: 0.9 | L4: 12 | M4: 2983.06 | N4: 90 | O4: 58 | P4: 2 | Q4: 2 | R4: 746 | S4: 683 | T4: 1 | U4: 0.33 | V4: 0 | W4: Rejected | X4: CIF | Y4: Amendment | Z4: January | AA4: 0.6603 | AB4: 0.8928 | AC4: 0.258912 | AD4: 1.01 | AE4: Extreme Risk | AF4: 0.025355825 | AG4: Average | AH4: High | AI4: Moderately Consistent | AJ4: 91.55496 | AK4: Average (85–94.99%) | AL4: 29.8306 | AM4: 1256310.4 | AN4: 71.44
A5: 319.4 | B5: 4.59 | C5: 15 | D5: 0.72 | E5: 0.02 | F5: 0.02 | G5: Road | H5: 4.49 | I5: 0.92 | J5: 1.18 | K5: 0.13 | L5: 2 | M5: 7687.09 | N5: 90 | O5: 15 | P5: 3 | Q5: 2 | R5: 275 | S5: 890 | T5: 3 | U5: 0.87 | V5: 1 | W5: Selected | X5: CIF | Y5: Extension | Z5: March | AA5: 0.7056 | AB5: 0.9604 | AC5: 0.268912 | AD5: 0.17 | AE5: Medium Risk | AF5: 0.014370695 | AG5: Poor | AH5: High | AI5: Highly Inconsistent | AJ5: 323.63636 | AK5: Over-Delivery (>100%) | AL5: 153.7418 | AM5: 2553649.2 | AN5: 82.51
A6: 120.21 | B6: 8.56 | C6: 23 | D6: 0.84 | E6: 0.04 | F6: 0.05 | G6: Road | H6: 2.26 | I6: 0.76 | J6: 0.94 | K6: 0.33 | L6: 9 | M6: 4154.52 | N6: 45 | O6: 11 | P6: 3 | Q6: 0 | R6: 171 | S6: 895 | T6: 1 | U6: 0.54 | V6: 0 | W6: Rejected | X6: EXW | Y6: Extension | Z6: January | AA6: 0.8064 | AB6: 0.912 | AC6: 0.14592 | AD6: 0.42 | AE6: High Risk | AF6: 0.071208718 | AG6: Good | AH6: Low | AI6: Inconsistent | AJ6: 523.39181 | AK6: Over-Delivery (>100%) | AL6: 83.0904 | AM6: 544450.71 | AN6: 83.54
A7: 120.2 | B7: 2.7 | C7: 29 | D7: 0.86 | E7: 0.09 | F7: 0.04 | G7: Air | H7: 2.03 | I7: 0.78 | J7: 1.06 | K7: 0.32 | L7: 35 | M7: 8881.56 | N7: 45 | O7: 49 | P7: 2 | Q7: 0 | R7: 54 | S7: 869 | T7: 6 | U7: 0.27 | V7: 0 | W7: Rejected | X7: EXW | Y7: Amendment | Z7: June | AA7: 0.7826 | AB7: 0.8736 | AC7: 0.122304 | AD7: 0.45 | AE7: High Risk | AF7: 0.022462562 | AG7: Average | AH7: Low | AI7: Inconsistent | AJ7: 1609.2593 | AK7: Over-Delivery (>100%) | AL7: 444.078 | AM7: 1206795.7 | AN7: 94.47
A8: 76.14 | B8: 7.05 | C8: 17 | D8: 0.97 | E8: 0.02 | F8: 0.05 | G8: Air | H8: 0.2 | I8: 0.86 | J8: 1.18 | K8: 0.8 | L8: 1 | M8: 9639.53 | N8: 15 | O8: 13 | P8: 2 | Q8: 0 | R8: 840 | S8: 10 | T8: 1 | U8: 0.54 | V8: 0 | W8: Rejected | X8: EXW | Y8: Amendment | Z8: January | AA8: 0.9506 | AB8: 0.931 | AC8: 0.02793 | AD8: 0.87 | AE8: Extreme Risk | AF8: 0.092592593 | AG8: Good | AH8: Low | AI8: Very Consistent | AJ8: 1.1904762 | AK8: Critical (<80%) | AL8: 481.9765 | AM8: 785812.86 | AN8: 98.2
A9: 439.78 | B9: 9.79 | C9: 7 | D9: 0.73 | E9: 0.07 | F9: 0.03 | G9: Air | H9: 1.82 | I9: 0.9 | J9: 1.12 | K9: 0.42 | L9: 46 | M9: 8612.09 | N9: 45 | O9: 44 | P9: 3 | Q9: 1 | R9: 790 | S9: 377 | T9: 2 | U9: 0.27 | V9: 0 | W9: Rejected | X9: FOB | Y9: Extension | Z9: February | AA9: 0.6789 | AB9: 0.9021 | AC9: 0.243567 | AD9: 0.52 | AE9: Extreme Risk | AF9: 0.022261131 | AG9: Average | AH9: High | AI9: Moderately Consistent | AJ9: 47.721519 | AK9: Critical (<80%) | AL9: 430.6045 | AM9: 4166614 | AN9: 95.48
A10: 320.5 | B10: 1.92 | C10: 28 | D10: 0.95 | E10: 0.07 | F10: 0.02 | G10: Air | H10: 4.25 | I10: 0.69 | J10: 1.08 | K10: 0.61 | L10: 31 | M10: 5273.99 | N10: 45 | O10: 50 | P10: 1 | Q10: 3 | R10: 34 | S10: 932 | T10: 9 | U10: 0.19 | V10: 0 | W10: Rejected | X10: DDP | Y10: Renewal/Reorder | Z10: September | AA10: 0.8835 | AB10: 0.9114 | AC10: 0.04557 | AD10: 0.7 | AE10: Extreme Risk | AF10: 0.0059906396 | AG10: Poor | AH10: High | AI10: Highly Inconsistent | AJ10: 2741.1765 | AK10: Over-Delivery (>100%) | AL10: 263.6995 | AM10: 1842733 | AN10: 93.25
A11: 368.63 | B11: 1.07 | C11: 14 | D11: 0.76 | E11: 0.04 | F11: 0.04 | G11: Air | H11: 3.8 | I11: 0.99 | J11: 1.19 | K11: 0.4 | L11: 28 | M11: 5147.1 | N11: 30 | O11: 50 | P11: 2 | Q11: 1 | R11: 904 | S11: 640 | T11: 11 | U11: 0.28 | V11: 1 | W11: Selected | X11: FOB | Y11: Amendment | Z11: November | AA11: 0.7296 | AB11: 0.9216 | AC11: 0.221184 | AD11: 0.48 | AE11: High Risk | AF11: 0.0029026395 | AG11: Poor | AH11: High | AI11: Highly Inconsistent | AJ11: 70.79646 | AK11: Critical (<80%) | AL11: 257.355 | AM11: 2049450.9 | AN11: 94.2
A12: 59.26 | B12: 4.9 | C12: 12 | D12: 0.82 | E12: 0.09 | F12: 0.04 | G12: Sea | H12: 1.1 | I12: 0.85 | J12: 0.87 | K12: 0.55 | L12: 45 | M12: 2237.14 | N12: 90 | O12: 44 | P12: 1 | Q12: 1 | R12: 309 | S12: 385 | T12: 1 | U12: 0.63 | V12: 1 | W12: Selected | X12: FOB | Y12: Renewal/Reorder | Z12: January | AA12: 0.7462 | AB12: 0.8736 | AC12: 0.157248 | AD12: 0.68 | AE12: Extreme Risk | AF12: 0.082686466 | AG12: Good | AH12: Low | AI12: Moderately Consistent | AJ12: 124.59547 | AK12: Over-Delivery (>100%) | AL12: 22.3714 | AM12: 149831.07 | AN12: 71.4
A13: 486.46 | B13: 1.83 | C13: 17 | D13: 0.79 | E13: 0.07 | F13: 0.05 | G13: Sea | H13: 2.07 | I13: 0.6 | J13: 1.11 | K13: 0.06 | L13: 37 | M13: 5963.55 | N13: 15 | O13: 37 | P13: 3 | Q13: 2 | R13: 234 | S13: 775 | T13: 4 | U13: 0.52 | V13: 1 | W13: Selected | X13: CIF | Y13: Extension | Z13: April | AA13: 0.7347 | AB13: 0.8835 | AC13: 0.185535 | AD13: 0.18 | AE13: Medium Risk | AF13: 0.0037618715 | AG13: Poor | AH13: High | AI13: Inconsistent | AJ13: 331.19658 | AK13: Over-Delivery (>100%) | AL13: 59.6355 | AM13: 3249231.7 | AN13: 70.83
... A3090: 312.32 | B3090: 2.54 | C3090: 16 | D3090: 0.75 | E3090: 0.02 | F3090: 0.03 | G3090: Sea | H3090: 1.85 | I3090: 0.9 | J3090: 0.85 | K3090: 0.09 | L3090: 11 | M3090: 6008.29 | N3090: 45 | O3090: 17 | P3090: 3 | Q3090: 0 | R3090: 204 | S3090: 519 | T3090: 4 | U3090: 0.86 | V3090: 1 | W3090: Selected | X3090: EXW | Y3090: Extension | Z3090: April | AA3090: 0.735 | AB3090: 0.9506 | AC3090: 0.23765 | AD3090: 0.14 | AE3090: Low Risk | AF3090: 0.0081326844 | AG3090: Poor | AH3090: High | AI3090: Moderately Consistent | AJ3090: 254.41176 | AK3090: Over-Delivery (>100%) | AL3090: 60.0829 | AM3090: 1970406.2 | AN3090: 72.95

Sheet Correlation_Analysis
A1: Metric | B1: Column in raw_data | C1: Correlation | D1: Strength | E1: Business Insight
A2: supplier_reliability_score | B2: U | C2: =CORREL(INDIRECT("MainTable!" & B2 & ":" & B2), MainTable!V:V) -> 0.010621748 | D2: =IF(ABS(C2) >= 0.05, "Moderate", IF(ABS(C2) >= 0.02, "Weak", "Very Weak")) -> Very Weak | E2: =IF(ABS(C2) < 0.01, "No meaningful relationship with selection", IF(C2 > 0, IF(ABS(C2) >= 0.02, "Slight tendency to be selected", "Minimal influence on selection"), IF(ABS(C2) >= 0.02, "Slight tendency to be rejected", "Minimal influence on selection"))) -> Minimal influence on selection
A3: quality_score | B3: B | C3: =CORREL(INDIRECT("MainTable!" & B3 & ":" & B3), MainTable!V:V) -> -0.0071605541 | D3: =IF(ABS(C3) >= 0.05, "Moderate", IF(ABS(C3) >= 0.02, "Weak", "Very Weak")) -> Very Weak | E3: =IF(ABS(C3) < 0.01, "No meaningful relationship with selection", IF(C3 > 0, IF(ABS(C3) >= 0.02, "Slight tendency to be selected", "Minimal influence on selection"), IF(ABS(C3) >= 0.02, "Slight tendency to be rejected", "Minimal influence on selection"))) -> No meaningful relationship with selection
A4: price_per_unit | B4: A | C4: =CORREL(INDIRECT("MainTable!" & B4 & ":" & B4), MainTable!V:V) -> -0.0092024582 | D4: =IF(ABS(C4) >= 0.05, "Moderate", IF(ABS(C4) >= 0.02, "Weak", "Very Weak")) -> Very Weak | E4: =IF(ABS(C4) < 0.01, "No meaningful relationship with selection", IF(C4 > 0, IF(ABS(C4) >= 0.02, "Slight tendency to be selected", "Minimal influence on selection"), IF(ABS(C4) >= 0.02, "Slight tendency to be rejected", "Minimal influence on selection"))) -> No meaningful relationship with selection
A5: on_time_delivery_rate | B5: D | C5: =CORREL(INDIRECT("MainTable!" & B5 & ":" & B5), MainTable!V:V) -> 0.0019591332 | D5: =IF(ABS(C5) >= 0.05, "Moderate", IF(ABS(C5) >= 0.02, "Weak", "Very Weak")) -> Very Weak | E5: =IF(ABS(C5) < 0.01, "No meaningful relationship with selection", IF(C5 > 0, IF(ABS(C5) >= 0.02, "Slight tendency to be selected", "Minimal influence on selection"), IF(ABS(C5) >= 0.02, "Slight tendency to be rejected", "Minimal influence on selection"))) -> No meaningful relationship with selection
A6: defect_rate | B6: E | C6: =CORREL(INDIRECT("MainTable!" & B6 & ":" & B6), MainTable!V:V) -> -0.035944134 | D6: =IF(ABS(C6) >= 0.05, "Moderate", IF(ABS(C6) >= 0.02, "Weak", "Very Weak")) -> Weak | E6: =IF(ABS(C6) < 0.01, "No meaningful relationship with selection", IF(C6 > 0, IF(ABS(C6) >= 0.02, "Slight tendency to be selected", "Minimal influence on selection"), IF(ABS(C6) >= 0.02, "Slight tendency to be rejected", "Minimal influence on selection"))) -> Slight tendency to be rejected
A7: return_rate | B7: F | C7: =CORREL(INDIRECT("MainTable!" & B7 & ":" & B7), MainTable!V:V) -> -0.010803821 | D7: =IF(ABS(C7) >= 0.05, "Moderate", IF(ABS(C7) >= 0.02, "Weak", "Very Weak")) -> Very Weak | E7: =IF(ABS(C7) < 0.01, "No meaningful relationship with selection", IF(C7 > 0, IF(ABS(C7) >= 0.02, "Slight tendency to be selected", "Minimal influence on selection"), IF(ABS(C7) >= 0.02, "Slight tendency to be rejected", "Minimal influence on selection"))) -> Minimal influence on selection
A8: delivery_time_days | B8: C | C8: =CORREL(INDIRECT("MainTable!" & B8 & ":" & B8), MainTable!V:V) -> 0.007650321 | D8: =IF(ABS(C8) >= 0.05, "Moderate", IF(ABS(C8) >= 0.02, "Weak", "Very Weak")) -> Very Weak | E8: =IF(ABS(C8) < 0.01, "No meaningful relationship with selection", IF(C8 > 0, IF(ABS(C8) >= 0.02, "Slight tendency to be selected", "Minimal influence on selection"), IF(ABS(C8) >= 0.02, "Slight tendency to be rejected", "Minimal influence on selection"))) -> No meaningful relationship with selection
A9: lead_time_variance | B9: H | C9: =CORREL(INDIRECT("MainTable!" & B9 & ":" & B9), MainTable!V:V) -> 0.0031792249 | D9: =IF(ABS(C9) >= 0.05, "Moderate", IF(ABS(C9) >= 0.02, "Weak", "Very Weak")) -> Very Weak | E9: =IF(ABS(C9) < 0.01, "No meaningful relationship with selection", IF(C9 > 0, IF(ABS(C9) >= 0.02, "Slight tendency to be selected", "Minimal influence on selection"), IF(ABS(C9) >= 0.02, "Slight tendency to be rejected", "Minimal influence on selection"))) -> No meaningful relationship with selection
A10: forecast_accuracy | B10: I | C10: =CORREL(INDIRECT("MainTable!" & B10 & ":" & B10), MainTable!V:V) -> -0.027081632 | D10: =IF(ABS(C10) >= 0.05, "Moderate", IF(ABS(C10) >= 0.02, "Weak", "Very Weak")) -> Weak | E10: =IF(ABS(C10) < 0.01, "No meaningful relationship with selection", IF(C10 > 0, IF(ABS(C10) >= 0.02, "Slight tendency to be selected", "Minimal influence on selection"), IF(ABS(C10) >= 0.02, "Slight tendency to be rejected", "Minimal influence on selection"))) -> Slight tendency to be rejected
A11: avg_order_volume | B11: M | C11: =CORREL(INDIRECT("MainTable!" & B11 & ":" & B11), MainTable!V:V) -> -0.016888622 | D11: =IF(ABS(C11) >= 0.05, "Moderate", IF(ABS(C11) >= 0.02, "Weak", "Very Weak")) -> Very Weak | E11: =IF(ABS(C11) < 0.01, "No meaningful relationship with selection", IF(C11 > 0, IF(ABS(C11) >= 0.02, "Slight tendency to be selected", "Minimal influence on selection"), IF(ABS(C11) >= 0.02, "Slight tendency to be rejected", "Minimal influence on selection"))) -> Minimal influence on selection
A12: order_frequency_monthy | B12: L | C12: =CORREL(INDIRECT("MainTable!" & B12 & ":" & B12), MainTable!V:V) -> 0.013228408 | D12: =IF(ABS(C12) >= 0.05, "Moderate", IF(ABS(C12) >= 0.02, "Weak", "Very Weak")) -> Very Weak | E12: =IF(ABS(C12) < 0.01, "No meaningful relationship with selection", IF(C12 > 0, IF(ABS(C12) >= 0.02, "Slight tendency to be selected", "Minimal influence on selection"), IF(ABS(C12) >= 0.02, "Slight tendency to be rejected", "Minimal influence on selection"))) -> Minimal influence on selection
A13: seasonality_index | B13: J | C13: =CORREL(INDIRECT("MainTable!" & B13 & ":" & B13), MainTable!V:V) -> 0.01534451 | D13: =IF(ABS(C13) >= 0.05, "Moderate", IF(ABS(C13) >= 0.02, "Weak", "Very Weak")) -> Very Weak | E13: =IF(ABS(C13) < 0.01, "No meaningful relationship with selection", IF(C13 > 0, IF(ABS(C13) >= 0.02, "Slight tendency to be selected", "Minimal influence on selection"), IF(ABS(C13) >= 0.02, "Slight tendency to be rejected", "Minimal influence on selection"))) -> Minimal influence on selection
... A25: customer_satisfaction | B25: AN | C25: =CORREL(INDIRECT("MainTable!" & B25 & ":" & B25), MainTable!V:V) -> 0.0047287011 | D25: =IF(ABS(C25) >= 0.05, "Moderate", IF(ABS(C25) >= 0.02, "Weak", "Very Weak")) -> Very Weak | E25: =IF(ABS(C25) < 0.01, "No meaningful relationship with selection", IF(C25 > 0, IF(ABS(C25) >= 0.02, "Slight tendency to be selected", "Minimal influence on selection"), IF(ABS(C25) >= 0.02, "Slight tendency to be rejected", "Minimal influence on selection"))) -> No meaningful relationship with selection

Sheet SummaryKPIs
A1: Category | B1: Suppliers Count | C1: Avg Delivery Performance | D1: Avg Accuracy | E1: Avg Risk | F1: Avg OTIF | G1: Avg Value | H1: Avg Fulfillment | I1: Avg shipping_cost | J1: Avg Total Cost Impact | K1: Avg Customer Satisfication
A2: Selected | B2: 1560 | C2: 0.80724744 | D2: 0.92730071 | E2: 0.57297436 | F2: 0.14034469 | G2: 0.027862836 | H2: 220.40693 | I2: 132.08189 | J2: 1449706.9 | K2: 83.485731
A3: Rejected | B3: 1529 | C3: 0.80504003 | D3: 0.92490687 | E3: 0.58315239 | F3: 0.14034619 | G3: 0.027608768 | H3: 251.07963 | I3: 135.46686 | J3: 1509690.8 | K3: 83.3924

Sheet KPIsPivots
B3: Suppliers Type
A4: KPIs | B4: Rejected | C4: Selected | D4: Difference
A5: Supplier Count | B5: 1529 | C5: 1560 | D5: =GETPIVOTDATA("Supplier Count",$A$3,"Suppliers Type","Selected")-GETPIVOTDATA("Supplier Count",$A$3,"Suppliers Type","Rejected") -> 31
A6: Delivery Performance | B6: 0.80504003 | C6: 0.80724744 | D6: =GETPIVOTDATA("Delivery Performance",$A$3,"Suppliers Type","Selected")-GETPIVOTDATA("Delivery Performance",$A$3,"Suppliers Type","Rejected") -> 0.0022074097
A7: Value | B7: 0.027608768 | C7: 0.027862836 | D7: =GETPIVOTDATA("Value",$A$3,"Suppliers Type","Selected")-GETPIVOTDATA("Value",$A$3,"Suppliers Type","Rejected") -> 0.00025406791
A8: Accuracy | B8: 0.92490687 | C8: 0.92730071 | D8: =GETPIVOTDATA("Accuracy",$A$3,"Suppliers Type","Selected")-GETPIVOTDATA("Accuracy",$A$3,"Suppliers Type","Rejected") -> 0.0023938379
A9: Risk | B9: 0.58315239 | C9: 0.57297436 | D9: =GETPIVOTDATA("Risk",$A$3,"Suppliers Type","Selected")-GETPIVOTDATA("Risk",$A$3,"Suppliers Type","Rejected") -> -0.010178028
A10: OTIF | B10: 0.14034619 | C10: 0.14034469 | D10: =GETPIVOTDATA("OTIF",$A$3,"Suppliers Type","Selected")-GETPIVOTDATA("OTIF",$A$3,"Suppliers Type","Rejected") -> -1.5019109e-06
A11: Fulfillment | B11: 251.07963 | C11: 220.40693 | D11: =GETPIVOTDATA("Fulfillment",$A$3,"Suppliers Type","Selected")-GETPIVOTDATA("Fulfillment",$A$3,"Suppliers Type","Rejected") -> -30.672701
A12: Shipping Cost | B12: 135.46686 | C12: 132.08189 | D12: =GETPIVOTDATA("Shipping Cost",$A$3,"Suppliers Type","Selected")-GETPIVOTDATA("Shipping Cost",$A$3,"Suppliers Type","Rejected") -> -3.3849703
A13: Total Cost Impact | B13: 1509690.8 | C13: 1449706.9 | D13: =GETPIVOTDATA("Total Cost Impact",$A$3,"Suppliers Type","Selected")-GETPIVOTDATA("Total Cost Impact",$A$3,"Suppliers Type","Rejected") -> -59983.86
A14: Customer Satisfication | B14: 83.3924 | C14: 83.485731 | D14: =GETPIVOTDATA("Customer Satisfication",$A$3,"Suppliers Type","Selected")-GETPIVOTDATA("Customer Satisfication",$A$3,"Suppliers Type","Rejected") -> 0.093330508
A19: KPIs | B19: Rejected | C19: Selected | D19: Difference | E19: Percentage of difference
A20: Fulfillment | B20: 251.07963 | C20: 220.40693 | D20: =GETPIVOTDATA("Fulfillment",$A$3,"Suppliers Type","Selected")-GETPIVOTDATA("Fulfillment",$A$3,"Suppliers Type","Rejected") -> -30.672701 | E20: =(Table3[[#This Row],[Selected]]-Table3[[#This Row],[Rejected]])/Table3[[#This Row],[Rejected]] -> -0.12216324
A21: Shipping Cost | B21: 135.46686 | C21: 132.08189 | D21: =GETPIVOTDATA("Shipping Cost",$A$3,"Suppliers Type","Selected")-GETPIVOTDATA("Shipping Cost",$A$3,"Suppliers Type","Rejected") -> -3.3849703 | E21: =(Table3[[#This Row],[Selected]]-Table3[[#This Row],[Rejected]])/Table3[[#This Row],[Rejected]] -> -0.024987442
A22: Total Cost Impact | B22: 1509690.8 | C22: 1449706.9 | D22: =GETPIVOTDATA("Total Cost Impact",$A$3,"Suppliers Type","Selected")-GETPIVOTDATA("Total Cost Impact",$A$3,"Suppliers Type","Rejected") -> -59983.86 | E22: =(Table3[[#This Row],[Selected]]-Table3[[#This Row],[Rejected]])/Table3[[#This Row],[Rejected]] -> -0.039732547
A28: KPIs | B28: Rejected | C28: Selected | D28: Difference | E28: Percentage of difference
A29: Delivery Performance | B29: 0.80504003 | C29: 0.80724744 | D29: =ROUND((GETPIVOTDATA("Delivery Performance",$A$3,"Suppliers Type","Selected")-GETPIVOTDATA("Delivery Performance",$A$3,"Suppliers Type","Rejected")), 4) -> 0.0022 | E29: =(Table6[[#This Row],[Selected]]-Table6[[#This Row],[Rejected]])/Table6[[#This Row],[Rejected]] -> 0.0027419876
A30: Value | B30: 0.027608768 | C30: 0.027862836 | D30: =ROUND((GETPIVOTDATA("Value",$A$3,"Suppliers Type","Selected")-GETPIVOTDATA("Value",$A$3,"Suppliers Type","Rejected")), 4) -> 0.0003 | E30: =(Table6[[#This Row],[Selected]]-Table6[[#This Row],[Rejected]])/Table6[[#This Row],[Rejected]] -> 0.0092024358
A31: Accuracy | B31: 0.92490687 | C31: 0.92730071 | D31: =ROUND((GETPIVOTDATA("Accuracy",$A$3,"Suppliers Type","Selected")-GETPIVOTDATA("Accuracy",$A$3,"Suppliers Type","Rejected")), 4) -> 0.0024 | E31: =(Table6[[#This Row],[Selected]]-Table6[[#This Row],[Rejected]])/Table6[[#This Row],[Rejected]] -> 0.0025881934
A32: Risk | B32: 0.58315239 | C32: 0.57297436 | D32: =ROUND((GETPIVOTDATA("Risk",$A$3,"Suppliers Type","Selected")-GETPIVOTDATA("Risk",$A$3,"Suppliers Type","Rejected")), 4) -> -0.0102 | E32: =(Table6[[#This Row],[Selected]]-Table6[[#This Row],[Rejected]])/Table6[[#This Row],[Rejected]] -> -0.017453462
A33: OTIF | B33: 0.14034619 | C33: 0.14034469 | D33: =GETPIVOTDATA("OTIF",$A$3,"Suppliers Type","Selected")-GETPIVOTDATA("OTIF",$A$3,"Suppliers Type","Rejected") -> -1.5019109e-06 | E33: =(Table6[[#This Row],[Selected]]-Table6[[#This Row],[Rejected]])/Table6[[#This Row],[Rejected]] -> -1.0701472e-05
A34: Customer Satisfication | B34: 83.3924 | C34: 83.485731 | D34: =GETPIVOTDATA("Customer Satisfication",$A$3,"Suppliers Type","Selected")-GETPIVOTDATA("Customer Satisfication",$A$3,"Suppliers Type","Rejected") -> 0.093330508 | E34: =(Table6[[#This Row],[Selected]]-Table6[[#This Row],[Rejected]])/Table6[[#This Row],[Rejected]] -> 0.0011191728
A38: KPIs | B38: Rejected | C38: Selected | D38: Difference
A39: Supplier Count | B39: 1529 | C39: 1560 | D39: =GETPIVOTDATA("Supplier Count",$A$3,"Suppliers Type","Selected")-GETPIVOTDATA("Supplier Count",$A$3,"Suppliers Type","Rejected") -> 31

Sheet CategoryDistributions
A1: category_type | B1: selection_status | C1: category | D1: count | E1: totals | F1: percentage_count
A2: risk | B2: Selected | C2: Low Risk | D2: 128 | E2: 3089 | F2: 4.14
A3: risk | B3: Rejected | C3: High Risk | D3: 326 | E3: 3089 | F3: 10.55
A4: risk | B4: Rejected | C4: Extreme Risk | D4: 886 | E4: 3089 | F4: 28.68
A5: risk | B5: Selected | C5: Medium Risk | D5: 230 | E5: 3089 | F5: 7.45
A6: risk | B6: Selected | C6: High Risk | D6: 310 | E6: 3089 | F6: 10.04
A7: risk | B7: Selected | C7: Extreme Risk | D7: 892 | E7: 3089 | F7: 28.88
A8: risk | B8: Rejected | C8: Low Risk | D8: 107 | E8: 3089 | F8: 3.46
A9: risk | B9: Rejected | C9: Medium Risk | D9: 210 | E9: 3089 | F9: 6.8
A10: value | B10: Selected | C10: Poor | D10: 774 | E10: 3089 | F10: 25.06
A11: value | B11: Rejected | C11: Poor | D11: 784 | E11: 3089 | F11: 25.38
A12: value | B12: Rejected | C12: Average | D12: 530 | E12: 3089 | F12: 17.16
A13: value | B13: Rejected | C13: Good | D13: 179 | E13: 3089 | F13: 5.79
... A43: fulfillment | B43: Rejected | C43: High (95–96.99%) | D43: 14 | E43: 3089 | F43: 0.45

Sheet CategoryPivots
A1: category_type | B1: (All)
A3: Sum of percentage_count | B3: Column Labels
A4: Row Labels | B4: Rejected | C4: Selected
A5: Average | B5: 17.16 | C5: 19
A6: Average (85–94.99%) | B6: 2.07 | C6: 2.69
A7: Critical (<80%) | B7: 20.04 | C7: 20.14
A8: Excellent | B8: 1.17 | C8: 1.59
A9: Extreme Risk | B9: 28.68 | C9: 28.88
A10: Good | B10: 5.79 | C10: 4.86
A11: High | B11: 22.14 | C11: 22.6
A12: High (95–96.99%) | B12: 0.45 | C12: 0.65
A13: High Risk | B13: 10.55 | C13: 10.04
A14: Highly Inconsistent | B14: 19.88 | C14: 20.14
A15: Inconsistent | B15: 9.61 | C15: 9.45
A16: Low | B16: 10.94 | C16: 11.65
... A25: World-Class (97%–100%) | B25: 0.68 | C25: 0.58

Sheet NumericParameterSummary
A1: Parameter | B1: Selected | C1: Rejected | D1: Difference | E1: Percentage Difference
A2: avg_order_volume | B2: 4955.0662 | C2: 5051.1047 | D2: -96.038465 | E2: -1.9
A3: defect_rate | B3: 0.048833333 | C3: 0.050961413 | D3: -0.0021280794 | E3: -4.18
A4: delivery_time_days | B4: 15.025 | C4: 14.896664 | D4: 0.12833551 | E4: 0.86
A5: demand_volatility_index | B5: 0.4990641 | C5: 0.50678875 | D5: -0.0077246483 | E5: -1.52
A6: forecast_accuracy | B6: 0.79785256 | C6: 0.80415958 | D6: -0.0063070173 | E6: -0.78
A7: items_offered | B7: 510.71282 | C7: 497.93264 | D7: 12.780185 | E7: 2.57
A8: items_requested | B8: 513.82372 | C8: 501.7482 | D8: 12.075517 | E8: 2.41
A9: lead_time_variance | B9: 2.5092692 | C9: 2.5000785 | D9: 0.0091907481 | E9: 0.37
A10: offer_validity_days | B10: 32.757051 | C10: 33.448005 | D10: -0.69095395 | E10: -2.07
A11: on_time_delivery_rate | B11: 0.84867949 | C11: 0.84834532 | D11: 0.00033416344 | E11: 0.04
A12: order_frequency_monthly | B12: 25.057692 | C12: 24.682799 | D12: 0.37489309 | E12: 1.52
A13: payment_term_days | B13: 48.596154 | C13: 47.992152 | D13: 0.60400211 | E13: 1.26
... A18: supplier_reliability_score | B18: 0.50832051 | C18: 0.50219097 | D18: 0.0061295383 | E18: 1.22

Sheet MonthlyPivot
A1: Count Of Selection Status | B1: Column Labels
A2: Row Labels | B2: Rejected | C2: Selected
A3: January | B3: 129 | C3: 143
A4: February | B4: 138 | C4: 149
A5: March | B5: 118 | C5: 118
A6: April | B6: 137 | C6: 110
A7: May | B7: 128 | C7: 134
A8: June | B8: 130 | C8: 128
A9: July | B9: 123 | C9: 124
A10: August | B10: 122 | C10: 114
A11: September | B11: 127 | C11: 136
A12: October | B12: 113 | C12: 132
A13: November | B13: 145 | C13: 127
A14: December | B14: 119 | C14: 145

Sheet Dashboard
